wqautils/__init__.py
wqautils/models.py
wqautils/utils.py
wqautils-0.1.0.dist-info/LICENSE
wqautils-0.1.0.dist-info/METADATA
wqautils-0.1.0.dist-info/WHEEL
wqautils-0.1.0.dist-info/RECORD
