Metadata-Version: 2.1
Name: wqautils
Version: 0.1.0
Summary: This Python package provides tools for water quality analysis, ensuring that key parameters like temperature, dissolved oxygen, conductivity, turbidity, and pH are within normal ranges. Using Pydantic for data validation, the package ensures accurate input handling and provides detailed explanations when values fall outside acceptable limits.
License: Apache 2.0
Author: jtdub
Author-email: james.williams@jtdub.com
Requires-Python: >=3.11,<4.0
Classifier: License :: Other/Proprietary License
Classifier: Programming Language :: Python :: 3
Classifier: Programming Language :: Python :: 3.11
Classifier: Programming Language :: Python :: 3.12
Classifier: Programming Language :: Python :: 3.13
Requires-Dist: pydantic (>=2.10.6,<3.0.0)
